run_r/__init__.py
run_r/run_r.py
run_r-0.2.5.dist-info/licenses/LICENSE
run_r-0.2.5.dist-info/METADATA
run_r-0.2.5.dist-info/WHEEL
run_r-0.2.5.dist-info/entry_points.txt
run_r-0.2.5.dist-info/top_level.txt
run_r-0.2.5.dist-info/RECORD
