Metadata-Version: 2.4
Name: run-r
Version: 0.2.5
Summary: A lightweight Python plugin to execute R scripts and retrieve workspace variables
Home-page: https://github.com/bsgarcia/run-r
Author: bsgarcia
Author-email: Your Name <your.email@example.com>
License: MIT
Project-URL: Homepage, https://github.com/bsgarcia/run-r
Project-URL: Repository, https://github.com/bsgarcia/run-r
Project-URL: Issues, https://github.com/bsgarcia/run-r/issues
Keywords: R,statistics,data-science,subprocess,interoperability
Classifier: Development Status :: 4 - Beta
Classifier: Intended Audience :: Developers
Classifier: Intended Audience :: Science/Research
Classifier: Topic :: Software Development :: Libraries :: Python Modules
Classifier: Topic :: Scientific/Engineering
Classifier: License :: OSI Approved :: MIT License
Classifier: Programming Language :: Python :: 3
Classifier: Programming Language :: Python :: 3.7
Classifier: Programming Language :: Python :: 3.8
Classifier: Programming Language :: Python :: 3.9
Classifier: Programming Language :: Python :: 3.10
Classifier: Programming Language :: Python :: 3.11
Classifier: Programming Language :: Python :: 3.12
Classifier: Operating System :: OS Independent
Requires-Python: >=3.7
License-File: LICENSE
Provides-Extra: dev
Requires-Dist: pytest>=7.0; extra == "dev"
Requires-Dist: pytest-cov>=3.0; extra == "dev"
Provides-Extra: pandas
Requires-Dist: pandas>=1.0.0; extra == "pandas"
Requires-Dist: numpy>=1.18.0; extra == "pandas"
Dynamic: author
Dynamic: home-page
Dynamic: license-file
Dynamic: requires-python
